extra_markers/__init__.py
extra_markers/markers.py
pytest_extra_markers-1.0.0.dist-info/LICENSE.txt
pytest_extra_markers-1.0.0.dist-info/METADATA
pytest_extra_markers-1.0.0.dist-info/WHEEL
pytest_extra_markers-1.0.0.dist-info/entry_points.txt
pytest_extra_markers-1.0.0.dist-info/top_level.txt
pytest_extra_markers-1.0.0.dist-info/RECORD
