Metadata-Version: 2.1
Name: pytest-extra-markers
Version: 1.0.0
Summary: Additional pytest markers to dynamically enable/disable tests viia CLI flags
Home-page: https://github.com/iwishiwasaneagle/pytest-extra-markers/
Author: iwishiwasaneagle
Author-email: jh.ewers@gmail.com
License: GPL-3.0-or-later
Project-URL: Source, https://github.com/iwishiwasaneagle/pytest-extra-markers/
Project-URL: Changelog, https://github.com/iwishiwasaneagle/pytest-extra-markers/blob/master/CHANGELOG.md
Project-URL: Issue Tracker, https://github.com/iwishiwasaneagle/pytest-extra-markers/issues/
Platform: Linux
Classifier: License :: OSI Approved :: GNU General Public License v3 or later (GPLv3+)
Classifier: Development Status :: 4 - Beta
Classifier: Natural Language :: English
Classifier: Framework :: Pytest
Classifier: Operating System :: OS Independent
Requires-Python: >=3.9
License-File: LICENSE.txt
Requires-Dist: pytest
Requires-Dist: importlib-metadata ; python_version < "3.8"
Provides-Extra: test
